{
    "source": "Twitter for iPhone",
    "entities": {
        "mentions": [
            {
                "start": 0,
                "end": 4,
                "username": "WHO",
                "id": "14499829"
            }
        ],
        "annotations": [
            {
                "start": 32,
                "end": 35,
                "probability": 0.9854,
                "type": "Place",
                "normalized_text": "Iran"
            }
        ]
    },
    "created_at": "2020-02-25T06:50:03.000Z",
    "id": "1232196039215632384",
    "text": "@WHO You were supposed to be in Iran today, can anyone tell us what's going on? Have you already sent the group you promised? We are anxious and really sick of hearing lies please let us know the truth.",
    "in_reply_to_user_id": "14499829"
}