{
    "entities": {
        "annotations": [
            {
                "start": 167,
                "end": 169,
                "probability": 0.8384,
                "type": "Other",
                "normalized_text": "God"
            }
        ]
    },
    "in_reply_to_user_id": "28972513",
    "created_at": "2020-03-21T22:55:10.000Z",
    "id": "1241498614603620354",
    "source": "Twitter for Android",
    "text": "@ali_ekuam Wait let me type this slowly...you know just because some people have a social gathering online,doesnt mean they cant meet you physically..n when they do,n God forbid ,us your real friends get exposed,that is the point...just follow government directive😠..okay night ekuam"
}