{
    "in_reply_to_user_id": "922669003159388160",
    "text": "@honestlyvibin @delaIuna Yesss, read about it and pick two more!!",
    "source": "Twitter for iPhone",
    "created_at": "2020-06-07T18:06:07.000Z",
    "entities": {
        "mentions": [
            {
                "start": 0,
                "end": 14,
                "username": "honestlyvibin",
                "id": "922669003159388160"
            },
            {
                "start": 15,
                "end": 24,
                "username": "delaIuna",
                "id": "1205333554508419072"
            }
        ]
    },
    "id": "1269692128428343296"
}