{
    "text": "“@Gizmodo: And here's a guy bending an iPhone 6 Plus with his bare hands http://t.co/M3PwzXCb5v http://t.co/lB5uvIDVUp” AKA, an idiot.",
    "created_at": "2014-09-23T23:42:15.000Z",
    "id": "514560404136402944",
    "entities": {
        "annotations": [
            {
                "start": 39,
                "end": 51,
                "probability": 0.5405,
                "type": "Product",
                "normalized_text": "iPhone 6 Plus"
            }
        ],
        "mentions": [
            {
                "start": 1,
                "end": 9,
                "username": "Gizmodo",
                "id": "2890961"
            }
        ],
        "urls": [
            {
                "start": 73,
                "end": 95,
                "url": "http://t.co/M3PwzXCb5v",
                "expanded_url": "http://gizmo.do/74dBvKC",
                "display_url": "gizmo.do/74dBvKC"
            },
            {
                "start": 96,
                "end": 118,
                "url": "http://t.co/lB5uvIDVUp",
                "expanded_url": "https://twitter.com/Gizmodo/status/514517470238240768/photo/1",
                "display_url": "pic.twitter.com/lB5uvIDVUp"
            }
        ]
    },
    "source": "Twitter for iPhone"
}