{
    "id": "514752924246110208",
    "in_reply_to_user_id": "1562935142",
    "source": "Twitter Web Client",
    "text": "what!!!!!!!!!!\n@BBCtrending https://t.co/OD5Vu2DojQ",
    "created_at": "2014-09-24T12:27:15.000Z",
    "entities": {
        "urls": [
            {
                "start": 28,
                "end": 51,
                "url": "https://t.co/OD5Vu2DojQ",
                "expanded_url": "https://twitter.com/BBCtrending/status/514395350615203841",
                "display_url": "twitter.com/BBCtrending/st…"
            }
        ],
        "mentions": [
            {
                "start": 15,
                "end": 27,
                "username": "BBCtrending",
                "id": "1562935142"
            }
        ]
    }
}