{
    "created_at": "2014-10-09T08:45:06.000Z",
    "source": "TweetDeck",
    "entities": {
        "urls": [
            {
                "start": 48,
                "end": 70,
                "url": "http://t.co/dAY74sPOpk",
                "expanded_url": "http://www.thepoke.co.uk/2014/10/08/penis-graffiti-drawn-on-1-5million-bugatti-veyron/",
                "display_url": "thepoke.co.uk/2014/10/08/pen…"
            },
            {
                "start": 71,
                "end": 93,
                "url": "http://t.co/dgHNkKsrjT",
                "expanded_url": "https://twitter.com/ThePoke/status/520132836594970625/photo/1",
                "display_url": "pic.twitter.com/dgHNkKsrjT"
            }
        ],
        "annotations": [
            {
                "start": 31,
                "end": 44,
                "probability": 0.4429,
                "type": "Product",
                "normalized_text": "Bugatti Veyron"
            }
        ]
    },
    "id": "520132836594970625",
    "text": "Penis graffiti  drawn on £1.5m Bugatti Veyron.\n\nhttp://t.co/dAY74sPOpk http://t.co/dgHNkKsrjT"
}