{
    "created_at": "2014-10-31 18:11:37+00:00",
    "id": 528247937118502912,
    "text": "@conncarroll @stephenfhayes I don't believe for 1 second Obama concerned mom's who stay home earn less 4 their sake-just less tax $ he gets",
    "entities": {
        "mentions": [
            {
                "start": 0,
                "end": 12,
                "username": "conncarroll",
                "id": "15739391"
            },
            {
                "start": 13,
                "end": 27,
                "username": "stephenfhayes",
                "id": "69773058"
            }
        ],
        "annotations": [
            {
                "start": 57,
                "end": 61,
                "probability": 0.9947,
                "type": "Person",
                "normalized_text": "Obama"
            }
        ]
    },
    "source": "Twitter Web Client",
    "in_reply_to_user_id": 15739391
}