{
    "created_at": "2014-11-03 04:13:55+00:00",
    "id": 529124286985170944,
    "text": "@fluffyguy @BigMeeze my guess is death by chocolate. Thats how I would wanna go.",
    "entities": {
        "mentions": [
            {
                "start": 0,
                "end": 10,
                "username": "fluffyguy",
                "id": "28245852"
            },
            {
                "start": 11,
                "end": 20,
                "username": "BigMeeze",
                "id": "45568474"
            }
        ]
    },
    "source": "Twitter for Android",
    "in_reply_to_user_id": 28245852
}