{
    "in_reply_to_user_id": "14173315",
    "entities": {
        "urls": [
            {
                "start": 60,
                "end": 82,
                "url": "http://t.co/B1XTZVhGds",
                "expanded_url": "http://nbcnews.to/1w0HtF0",
                "display_url": "nbcnews.to/1w0HtF0"
            },
            {
                "start": 83,
                "end": 105,
                "url": "http://t.co/x6nRAa7fgl",
                "expanded_url": "https://twitter.com/NBCNews/status/543586319168196608/photo/1",
                "display_url": "pic.twitter.com/x6nRAa7fgl"
            }
        ],
        "annotations": [
            {
                "start": 23,
                "end": 26,
                "probability": 0.6578,
                "type": "Person",
                "normalized_text": "Pope"
            }
        ],
        "mentions": [
            {
                "start": 1,
                "end": 9,
                "username": "NBCNews",
                "id": "14173315"
            },
            {
                "start": 107,
                "end": 118,
                "username": "sandynoahz",
                "id": "2839368536"
            }
        ]
    },
    "source": "Twitter for iPad",
    "created_at": "2014-12-13T04:40:15.000Z",
    "text": "“@NBCNews: New dog-ma? Pope says heaven is for hounds, too\n http://t.co/B1XTZVhGds http://t.co/x6nRAa7fgl” @sandynoahz",
    "id": "543626431314407424"
}