{
    "entities": {
        "urls": [
            {
                "start": 59,
                "end": 81,
                "url": "http://t.co/oOUnVB5RZg",
                "expanded_url": "http://huzlers.com/bobby-shmurda-stabbed-death-rikers-island-jail-cell-mate/",
                "display_url": "huzlers.com/bobby-shmurda-…"
            },
            {
                "start": 82,
                "end": 104,
                "url": "http://t.co/EjlTkCIMey",
                "expanded_url": "https://twitter.com/TheHuzlers/status/548672230134382592/photo/1",
                "display_url": "pic.twitter.com/EjlTkCIMey"
            }
        ],
        "mentions": [
            {
                "start": 1,
                "end": 12,
                "username": "TheHuzlers",
                "id": "2302467404"
            }
        ],
        "annotations": [
            {
                "start": 14,
                "end": 26,
                "probability": 0.9961,
                "type": "Person",
                "normalized_text": "Bobby Shmurda"
            }
        ]
    },
    "source": "Twitter for iPhone",
    "text": "“@TheHuzlers: Bobby Shmurda Stabbed To Death By Cell Mate\n\nhttp://t.co/oOUnVB5RZg http://t.co/EjlTkCIMey”\n\nPeople deadass believe this 💀",
    "created_at": "2014-12-27T05:03:40.000Z",
    "id": "548705752941330433",
    "in_reply_to_user_id": "2302467404"
}