{
    "created_at": "2015-01-10 19:16:15+00:00",
    "id": 553993744102752256,
    "text": "@vtchakarova he probably found truth about who is really behind this ? And got killed ? Sick people http://t.co/MEnznQsseZ",
    "entities": {
        "mentions": [
            {
                "start": 0,
                "end": 12,
                "username": "vtchakarova",
                "id": "424083365"
            }
        ],
        "urls": [
            {
                "start": 100,
                "end": 122,
                "url": "http://t.co/MEnznQsseZ",
                "expanded_url": "https://twitter.com/of_meh/status/553993744102752256/photo/1",
                "display_url": "pic.twitter.com/MEnznQsseZ"
            }
        ]
    },
    "source": "Twitter for iPhone",
    "in_reply_to_user_id": 424083365
}