{
    "created_at": "2015-06-27 02:52:03+00:00",
    "id": 614627222431924224,
    "text": "@petesouza @ChazDragoon The Empire State Building is the one I like.",
    "entities": {
        "mentions": [
            {
                "start": 0,
                "end": 10,
                "username": "PeteSouza",
                "id": "1257689418888089600"
            }
        ],
        "annotations": [
            {
                "start": 28,
                "end": 48,
                "probability": 0.3696,
                "type": "Organization",
                "normalized_text": "Empire State Building"
            }
        ]
    },
    "source": "Twitter Web Client",
    "in_reply_to_user_id": 18215973
}