{
    "id": "1239491045525766144",
    "created_at": "2020-03-16T09:57:48.000Z",
    "entities": {
        "hashtags": [
            {
                "start": 95,
                "end": 111,
                "tag": "LetsFightCorona"
            }
        ],
        "mentions": [
            {
                "start": 112,
                "end": 119,
                "username": "MenPk1",
                "id": "1199282153852407810"
            },
            {
                "start": 120,
                "end": 136,
                "username": "TeamForPakistan",
                "id": "1216367880209666048"
            }
        ]
    },
    "text": "This is why it is important to stay more than 1 meter (3 feet) away from a person who is sick.\n#LetsFightCorona @MenPk1\n@TeamForPakistan",
    "in_reply_to_user_id": "1199282153852407810",
    "source": "Twitter Web App"
}