{
    "created_at": "2020-04-06 12:41:42+00:00",
    "id": 1247142437925027840,
    "text": "@monteblan @ruskin147 Bro. Fucking google it your damn self.\nhttps://t.co/pTif2EYGdt",
    "entities": {
        "mentions": [
            {
                "start": 0,
                "end": 10,
                "username": "monteblan",
                "id": "83820512"
            },
            {
                "start": 11,
                "end": 21,
                "username": "ruskin147",
                "id": "1294741"
            }
        ],
        "urls": [
            {
                "start": 61,
                "end": 84,
                "url": "https://t.co/pTif2EYGdt",
                "expanded_url": "https://lmgtfy.com/?q=what+is+5G%3F",
                "display_url": "lmgtfy.com/?q=what+is+5G%\u2026",
                "status": 200,
                "unwound_url": "https://lmgtfy.app/?q=what+is+5G%3F"
            }
        ]
    },
    "source": "Twitter for iPad",
    "in_reply_to_user_id": 83820512
}