{
    "created_at": "2014-11-01 22:35:02+00:00",
    "id": 528676615207653376,
    "text": "Fanged deer spotted in Afghanistan for the first time in 65 years http://t.co/u48JG33IGc http://t.co/dm57teqbR8",
    "entities": {
        "annotations": [
            {
                "start": 23,
                "end": 33,
                "probability": 0.9833,
                "type": "Place",
                "normalized_text": "Afghanistan"
            }
        ],
        "urls": [
            {
                "start": 66,
                "end": 88,
                "url": "http://t.co/u48JG33IGc",
                "expanded_url": "http://i100.io/SDJe9oM",
                "display_url": "i100.io/SDJe9oM"
            },
            {
                "start": 89,
                "end": 111,
                "url": "http://t.co/dm57teqbR8",
                "expanded_url": "https://twitter.com/Independent/status/528676615207653376/photo/1",
                "display_url": "pic.twitter.com/dm57teqbR8"
            }
        ]
    },
    "source": "TweetDeck",
    "in_reply_to_user_id": null
}