{
    "in_reply_to_user_id": "1377719425",
    "source": "Twitter Web Client",
    "entities": {
        "mentions": [
            {
                "start": 19,
                "end": 32,
                "username": "assholeofday",
                "id": "1377719425"
            }
        ],
        "hashtags": [
            {
                "start": 0,
                "end": 18,
                "tag": "MYNEWTINDEROPENER"
            }
        ]
    },
    "created_at": "2015-02-15T16:42:23.000Z",
    "text": "#MYNEWTINDEROPENER @assholeofday @LauraPalmer198",
    "id": "567000983491072000"
}